{
	"_transient": null,
	"attributes": {
		"AT31_EDADBAQA369": {
			"attributeId": "AT31_EDADBAQA369",
			"autoGeneratedStr": "F",
			"columnName": null,
			"customizationLayer": 0,
			"customizationLayerDescription": "ECU",
			"dataType": "Integer",
			"entityPk": {
				"entityId": "EN_CLIENTEYA_369",
				"version": "1.0.0"
			},
			"expression": null,
			"falseValue": null,
			"labelId": null,
			"length": 0,
			"listValues": null,
			"name": "edad",
			"objectType": null,
			"order": 2,
			"pkStr": "F",
			"requiredStr": "F",
			"transientStr": "F",
			"trueValue": null
		},
		"AT45_IDCLIENN369": {
			"attributeId": "AT45_IDCLIENN369",
			"autoGeneratedStr": "F",
			"columnName": null,
			"customizationLayer": 0,
			"customizationLayerDescription": "ECU",
			"dataType": "Integer",
			"entityPk": {
				"entityId": "EN_CLIENTEYA_369",
				"version": "1.0.0"
			},
			"expression": null,
			"falseValue": null,
			"labelId": null,
			"length": 0,
			"listValues": null,
			"name": "idCliente",
			"objectType": null,
			"order": 1,
			"pkStr": "F",
			"requiredStr": "T",
			"transientStr": "F",
			"trueValue": null
		}
	},
	"customizationLayer": 0,
	"customizationLayerDescription": "ECU",
	"databaseName": null,
	"dbmsName": null,
	"description": null,
	"id": {
		"entityId": "EN_CLIENTEYA_369",
		"version": "1.0.0"
	},
	"isAutomatic": false,
	"isImported": false,
	"moduleId": "MMBGN",
	"name": {
		"$ref": "../../MMBGN/relations/componentKeys.json#/Entities/EN_CLIENTEYA_369/name"
	},
	"related": false,
	"tableName": null,
	"transient": null
}
